reusable/__init__.py
reusable/config.py
reusable/datetime_functions.py
reusable/fake_useragent.py
reusable/functions.py
reusable/iterable_functions.py
reusable/network_functions.py
reusable/string_functions.py
reusable/utility_functions.py
reusable/data/useragents.txt
reusable-0.0.9.dist-info/AUTHORS.rst
reusable-0.0.9.dist-info/LICENSE
reusable-0.0.9.dist-info/METADATA
reusable-0.0.9.dist-info/WHEEL
reusable-0.0.9.dist-info/top_level.txt
reusable-0.0.9.dist-info/RECORD
